LICENSE
directbank/models/__init__.py
directbank/models/Camt.py
directbank/models/CancelationRequest.py
directbank/models/ExchCommon.py
directbank/models/Letter.py
directbank/models/Packet.py
directbank/models/Pain.py
directbank/models/PayDocRu.py
directbank/models/PayRequest.py
directbank/models/Probe.py
directbank/models/ResultBank.py
directbank/models/Settings.py
directbank/models/Statement.py
directbank/models/StatementRequest.py
directbank/models/StatusDocNotice.py
directbank/models/StatusPacketNotice.py
directbank/models/StatusRequest.py
directbank/models/X509Data.py
directbank/views/__init__.py
directbank-1.0.2.dist-info/LICENSE
directbank-1.0.2.dist-info/WHEEL
directbank-1.0.2.dist-info/METADATA
directbank-1.0.2.dist-info/RECORD
