Metadata-Version: 2.1
Name: directbank
Version: 1.0.2
Summary: 
Home-page: https://gitlab.com/kizyanov/directbank
License: MIT
Keywords: directbank
Author: Toony
Author-email: kizyanov@protonmail.com
Requires-Python: >=3.9,<4.0
Classifier: License :: OSI Approved :: MIT License
Classifier: Programming Language :: Python :: 3
Classifier: Programming Language :: Python :: 3.10
Classifier: Programming Language :: Python :: 3.9
Classifier: Topic :: Software Development :: Documentation
Classifier: Topic :: Software Development :: Libraries :: Python Modules
Requires-Dist: xsdata (==22.4)
Project-URL: Repository, https://gitlab.com/kizyanov/directbank
